pydevlpr_protocol/__init__.py
pydevlpr_protocol/protocol.py
pydevlpr_protocol-0.1.2.dist-info/LICENSE
pydevlpr_protocol-0.1.2.dist-info/WHEEL
pydevlpr_protocol-0.1.2.dist-info/METADATA
pydevlpr_protocol-0.1.2.dist-info/RECORD
